mixpython/__init__.py
mixpython/algorithms.py
mixpython-0.1.0.dist-info/LICENSE
mixpython-0.1.0.dist-info/METADATA
mixpython-0.1.0.dist-info/WHEEL
mixpython-0.1.0.dist-info/top_level.txt
mixpython-0.1.0.dist-info/RECORD
