Metadata-Version: 2.1
Name: mixpython
Version: 0.1.0
Summary: mix
Home-page: https://github.com/sth-v/mixpython
Author: Andrew Astakhov
Author-email: aw.astakhov@gmail.com
License: UNKNOWN
Project-URL: Bug Tracker, https://github.com/sth-v/mixpython/issues
Platform: UNKNOWN
Classifier: Programming Language :: Python :: 3
Classifier: License :: OSI Approved :: MIT License
Classifier: Operating System :: OS Independent
Requires-Python: >=3.6
License-File: LICENSE
